django_email_auth/__init__.py
django_email_auth/apps.py
django_email_auth/backend.py
django_email_auth/management/__init__.py
django_email_auth/management/commands/__init__.py
django_email_auth/management/commands/create_admin.py
django_email_auth/tests/__init__.py
django_email_auth/tests/conftest.py
django_email_auth/tests/test_create_admin.py
django_email_auth/tests/test_custom_auth.py
django_email_auth_backend-1.0.0.dist-info/LICENSE
django_email_auth_backend-1.0.0.dist-info/METADATA
django_email_auth_backend-1.0.0.dist-info/WHEEL
django_email_auth_backend-1.0.0.dist-info/RECORD
